istrulab/__init__.py
istrulab-0.0.1.dist-info/METADATA
istrulab-0.0.1.dist-info/WHEEL
istrulab-0.0.1.dist-info/top_level.txt
istrulab-0.0.1.dist-info/RECORD
